deampy/__init__.py
deampy/calibration.py
deampy/data_structure.py
deampy/decision_tree.py
deampy/discrete_event_sim.py
deampy/econ_eval.py
deampy/format_functions.py
deampy/in_out_functions.py
deampy/markov.py
deampy/models.py
deampy/parameter_estimation.py
deampy/parameters.py
deampy/random_variates.py
deampy/regression_models.py
deampy/sample_path.py
deampy/sensitivity_analysis.py
deampy/statistics.py
deampy/optimization/__init__.py
deampy/optimization/appx_policy_itr.py
deampy/optimization/learning_exploring_rules.py
deampy/optimization/opt_support.py
deampy/optimization/stoch_approx.py
deampy/plots/__init__.py
deampy/plots/econ_eval_plots.py
deampy/plots/histogram.py
deampy/plots/plot_support.py
deampy/plots/pop_pyramids.py
deampy/plots/prob_dists.py
deampy/plots/sample_paths.py
deampy/plots/sample_size.py
deampy/support/__init__.py
deampy/support/econ_eval_support.py
deampy/support/misc_classes.py
deampy/support/misc_functions.py
deampy/support/simulation.py
deampy-1.5.7.dist-info/licenses/LICENSE
deampy-1.5.7.dist-info/METADATA
deampy-1.5.7.dist-info/WHEEL
deampy-1.5.7.dist-info/top_level.txt
deampy-1.5.7.dist-info/RECORD
