Metadata-Version: 2.4
Name: deampy
Version: 1.5.7
Summary: Decision analysis in medicine and public health
Home-page: https://github.com/modeling-health-care-decisions/deampy
Author: Reza Yaesoubi
Author-email: reza.yaesoubi@yale.edu
License: MIT License
License-File: LICENSE
Requires-Dist: numpy
Requires-Dist: numba
Requires-Dist: matplotlib
Requires-Dist: scipy
Requires-Dist: statsmodels
Requires-Dist: scikit-learn
Requires-Dist: pandas
Requires-Dist: seaborn
Dynamic: author
Dynamic: author-email
Dynamic: description
Dynamic: home-page
Dynamic: license
Dynamic: license-file
Dynamic: requires-dist
Dynamic: summary
